[
  {
    "timestamp": "2026-01-27 21:56:31",
    "operation": "UPDATE",
    "table": "crm_ai_web.user",
    "where": [
      "'cmkb4qu3r0003pawcy2sc5vyh'",
      "'admin@company.co.kr'",
      "'愿由ъ옄'",
      "'$2b$10$.iatb8PCiF5FNqidKFEI4e/qTxCgwWe.r8O7mpIdKTOhzrW8CNvW6'",
      "'ADMIN'",
      "1",
      "5",
      "'2026-01-12 12:19:15.302'",
      "'2026-01-27 12:47:56.082'",
      "0",
      "1",
      "0",
      "'2026-01-27 07:06:29.314'",
      "NULL",
      "NULL",
      "NULL"
    ],
    "set": [
      "'cmkb4qu3r0003pawcy2sc5vyh'",
      "'admin@company.co.kr'",
      "'愿由ъ옄'",
      "'$2b$10$IRdxVHTZDeb.46YHnd/TAOW/NNitmGOLsICqH5cNYzc0OePPA1Sve'",
      "'ADMIN'",
      "1",
      "5",
      "'2026-01-12 12:19:15.302'",
      "'2026-01-27 12:56:31.103'",
      "0",
      "1",
      "0",
      "'2026-01-27 07:06:29.314'",
      "NULL",
      "NULL",
      "NULL"
    ],
    "mode": "SET"
  },
  {
    "timestamp": "2026-01-28 13:18:21",
    "operation": "INSERT",
    "table": "crm_ai_web.customer",
    "values": [
      "'cmkxim0tt00005z7htm9x1j3p'",
      "'?대???",
      "'010-3859-6284@temp.com'",
      "'010-3859-6284'",
      "NULL",
      "'ACTIVE'",
      "NULL",
      "'NORMAL'",
      "0",
      "NULL",
      "'2026-01-28 04:18:21.231'",
      "'2026-01-28 04:18:21.231'"
    ],
    "mode": "SET"
  },
  {
    "timestamp": "2026-01-28 13:18:21",
    "operation": "INSERT",
    "table": "crm_ai_web.afterservice",
    "values": [
      "'cmkxim0u100025z7hxqpr178o'",
      "'AS-20260128-001'",
      "'AS-20260128-001'",
      "'cmkxim0tt00005z7htm9x1j3p'",
      "NULL",
      "'?대???",
      "'REPAIR'",
      "'NOISE'",
      "'RECEIVED'",
      "'NORMAL'",
      "'???뚯쓬 - ?섎━鍮?2留뚯썝 ?덈궡??",
      "'??",
      "''",
      "NULL",
      "NULL",
      "NULL",
      "NULL",
      "'2026-01-28 04:18:21.239'",
      "'2026-01-28 04:18:21.242'",
      "NULL",
      "NULL",
      "NULL",
      "'2026-01-28 04:18:21.242'",
      "'2026-01-28 04:18:21.242'",
      "''",
      "''",
      "'遺?곗떆 ?숇옒援?李⑤강怨⑤줈 24 ?꾩씠?덉뒪 501??",
      "'010-3859-6284'",
      "NULL",
      "NULL",
      "NULL",
      "NULL",
      "''",
      "NULL",
      "''"
    ],
    "mode": "SET"
  },
  {
    "timestamp": "2026-01-28 13:18:35",
    "operation": "UPDATE",
    "table": "crm_ai_web.afterservice",
    "where": [
      "'cmkxim0u100025z7hxqpr178o'",
      "'AS-20260128-001'",
      "'AS-20260128-001'",
      "'cmkxim0tt00005z7htm9x1j3p'",
      "NULL",
      "'?대???",
      "'REPAIR'",
      "'NOISE'",
      "'RECEIVED'",
      "'NORMAL'",
      "'???뚯쓬 - ?섎━鍮?2留뚯썝 ?덈궡??",
      "'??",
      "''",
      "NULL",
      "NULL",
      "NULL",
      "NULL",
      "'2026-01-28 04:18:21.239'",
      "'2026-01-28 04:18:21.242'",
      "NULL",
      "NULL",
      "NULL",
      "'2026-01-28 04:18:21.242'",
      "'2026-01-28 04:18:21.242'",
      "''",
      "''",
      "'遺?곗떆 ?숇옒援?李⑤강怨⑤줈 24 ?꾩씠?덉뒪 501??",
      "'010-3859-6284'",
      "NULL",
      "NULL",
      "NULL",
      "NULL",
      "''",
      "NULL",
      "''"
    ],
    "set": [
      "'cmkxim0u100025z7hxqpr178o'",
      "'AS-20260128-001'",
      "'AS-20260128-001'",
      "'cmkxim0tt00005z7htm9x1j3p'",
      "NULL",
      "'?대???",
      "'REPAIR'",
      "'NOISE'",
      "'AS'",
      "'NORMAL'",
      "'???뚯쓬 - ?섎━鍮?2留뚯썝 ?덈궡??",
      "'??",
      "''",
      "NULL",
      "NULL",
      "NULL",
      "NULL",
      "'2026-01-28 04:18:21.239'",
      "'2026-01-28 04:18:21.242'",
      "NULL",
      "NULL",
      "NULL",
      "'2026-01-28 04:18:21.242'",
      "'2026-01-28 04:18:35.136'",
      "''",
      "''",
      "'遺?곗떆 ?숇옒援?李⑤강怨⑤줈 24 ?꾩씠?덉뒪 501??",
      "'010-3859-6284'",
      "NULL",
      "'2026-01-28 00:00:00.000'",
      "NULL",
      "NULL",
      "''",
      "NULL",
      "''"
    ],
    "mode": "SET"
  },
  {
    "timestamp": "2026-01-28 13:18:48",
    "operation": "UPDATE",
    "table": "crm_ai_web.afterservice",
    "where": [
      "'cmkxim0u100025z7hxqpr178o'",
      "'AS-20260128-001'",
      "'AS-20260128-001'",
      "'cmkxim0tt00005z7htm9x1j3p'",
      "NULL",
      "'?대???",
      "'REPAIR'",
      "'NOISE'",
      "'AS'",
      "'NORMAL'",
      "'???뚯쓬 - ?섎━鍮?2留뚯썝 ?덈궡??",
      "'??",
      "''",
      "NULL",
      "NULL",
      "NULL",
      "NULL",
      "'2026-01-28 04:18:21.239'",
      "'2026-01-28 04:18:21.242'",
      "NULL",
      "NULL",
      "NULL",
      "'2026-01-28 04:18:21.242'",
      "'2026-01-28 04:18:35.136'",
      "''",
      "''",
      "'遺?곗떆 ?숇옒援?李⑤강怨⑤줈 24 ?꾩씠?덉뒪 501??",
      "'010-3859-6284'",
      "NULL",
      "'2026-01-28 00:00:00.000'",
      "NULL",
      "NULL",
      "''",
      "NULL",
      "''"
    ],
    "set": [
      "'cmkxim0u100025z7hxqpr178o'",
      "'AS-20260128-001'",
      "'AS-20260128-001'",
      "'cmkxim0tt00005z7htm9x1j3p'",
      "NULL",
      "'?대???",
      "'REPAIR'",
      "'NOISE'",
      "'AS'",
      "'NORMAL'",
      "'???뚯쓬 - ?섎━鍮?2留뚯썝 ?덈궡??",
      "'??",
      "''",
      "NULL",
      "NULL",
      "NULL",
      "NULL",
      "'2026-01-28 04:18:21.239'",
      "'2026-01-28 04:18:21.242'",
      "NULL",
      "NULL",
      "NULL",
      "'2026-01-28 04:18:21.242'",
      "'2026-01-28 04:18:48.385'",
      "'蹂몄궗'",
      "''",
      "'遺?곗떆 ?숇옒援?李⑤강怨⑤줈 24 ?꾩씠?덉뒪 501??",
      "'010-3859-6284'",
      "NULL",
      "'2026-01-28 00:00:00.000'",
      "NULL",
      "NULL",
      "''",
      "NULL",
      "''"
    ],
    "mode": "SET"
  },
  {
    "timestamp": "2026-01-28 13:24:37",
    "operation": "UPDATE",
    "table": "crm_ai_web.afterservice",
    "where": [
      "'cmkqiqfzz0222o40sjdpar3wo'",
      "'AS-20260123-002'",
      "'AS-20260123-002'",
      "'cmkqiqfzr0220o40s52o9cxgy'",
      "NULL",
      "'?⑹쑄誘?",
      "'REPAIR'",
      "'NOISE'",
      "'AS'",
      "'NORMAL'",
      "'湲곌린?먯꽌 ?뚯쓬 諛쒖깮(鍮④컙??遺덈튆?먯꽌留??뚯쓬??諛쒖깮?섏? ?딆쓬)'",
      "'?대뱶3'",
      "''",
      "NULL",
      "NULL",
      "NULL",
      "NULL",
      "'2026-01-23 06:47:24.285'",
      "'2026-01-23 06:47:24.287'",
      "NULL",
      "NULL",
      "NULL",
      "'2026-01-23 06:47:24.287'",
      "'2026-01-27 07:13:12.118'",
      "'洹몃줈??",
      "''",
      "'寃쎄린??愿묒＜???쒖꽦濡?5 ?쒖쟾?먯뒪?뚯씠??1501??902??",
      "'010-3796-7463'",
      "'2026-01-27 00:00:00.000'",
      "'2026-01-23 00:00:00.000'",
      "NULL",
      "'2023-09-25 00:00:00.000'",
      "'?щえ??援먯껜. ?대?泥?냼?꾨즺. 洹몃줈?몄뿉 25,000??泥?뎄.'",
      "NULL",
      "''"
    ],
    "set": [
      "'cmkqiqfzz0222o40sjdpar3wo'",
      "'AS-20260123-002'",
      "'AS-20260123-002'",
      "'cmkqiqfzr0220o40s52o9cxgy'",
      "NULL",
      "'?⑹쑄誘?",
      "'REPAIR'",
      "'NOISE'",
      "'AS'",
      "'NORMAL'",
      "'湲곌린?먯꽌 ?뚯쓬 諛쒖깮(鍮④컙??遺덈튆?먯꽌留??뚯쓬??諛쒖깮?섏? ?딆쓬)'",
      "'?대뱶3'",
      "''",
      "NULL",
      "NULL",
      "NULL",
      "NULL",
      "'2026-01-23 06:47:24.285'",
      "'2026-01-23 06:47:24.287'",
      "NULL",
      "NULL",
      "NULL",
      "'2026-01-23 06:47:24.287'",
      "'2026-01-28 04:24:37.246'",
      "'洹몃줈??",
      "''",
      "'寃쎄린??愿묒＜???쒖꽦濡?5 ?쒖쟾?먯뒪?뚯씠??1501??902??",
      "'010-3796-7463'",
      "'2026-01-27 00:00:00.000'",
      "'2026-01-23 00:00:00.000'",
      "'2026-01-28 00:00:00.000'",
      "'2023-09-25 00:00:00.000'",
      "'?щえ??援먯껜. ?대?泥?냼?꾨즺. 洹몃줈?몄뿉 25,000??泥?뎄.'",
      "'2026-01-28 00:00:00.000'",
      "'461466043393'"
    ],
    "mode": "SET"
  },
  {
    "timestamp": "2026-01-28 13:34:40",
    "operation": "INSERT",
    "table": "crm_ai_web.customer",
    "values": [
      "'cmkxj704q00035z7hg5br0t7h'",
      "'?뺤???",
      "'010-2570-1521@temp.com'",
      "'010-2570-1521'",
      "NULL",
      "'ACTIVE'",
      "NULL",
      "'NORMAL'",
      "0",
      "NULL",
      "'2026-01-28 04:34:40.106'",
      "'2026-01-28 04:34:40.106'"
    ],
    "mode": "SET"
  },
  {
    "timestamp": "2026-01-28 13:34:40",
    "operation": "INSERT",
    "table": "crm_ai_web.afterservice",
    "values": [
      "'cmkxj704u00055z7hneamhm2q'",
      "'AS-20260128-002'",
      "'AS-20260128-002'",
      "'cmkxj704q00035z7hg5br0t7h'",
      "NULL",
      "'?뺤???",
      "'REPAIR'",
      "'OTHER'",
      "'RECEIVED'",
      "'NORMAL'",
      "'異⑹쟾???섏??딆쑝硫? 異⑹쟾???곌껐?먮룄 諛섏쓳???놁뒿?덈떎.'",
      "'??'",
      "''",
      "NULL",
      "NULL",
      "NULL",
      "NULL",
      "'2026-01-28 04:34:40.104'",
      "'2026-01-28 04:34:40.110'",
      "NULL",
      "NULL",
      "NULL",
      "'2026-01-28 04:34:40.110'",
      "'2026-01-28 04:34:40.110'",
      "'洹몃줈??",
      "''",
      "'寃쎈궓 吏꾩＜??異⑹쓽濡?146(以묓씎 S?대옒???뷀띁?ㅽ듃) 605??602??",
      "'010-2570-1521'",
      "NULL",
      "NULL",
      "NULL",
      "'2024-06-30 00:00:00.000'",
      "''",
      "NULL",
      "''"
    ],
    "mode": "SET"
  },
  {
    "timestamp": "2026-01-28 13:34:59",
    "operation": "UPDATE",
    "table": "crm_ai_web.afterservice",
    "where": [
      "'cmkxj704u00055z7hneamhm2q'",
      "'AS-20260128-002'",
      "'AS-20260128-002'",
      "'cmkxj704q00035z7hg5br0t7h'",
      "NULL",
      "'?뺤???",
      "'REPAIR'",
      "'OTHER'",
      "'RECEIVED'",
      "'NORMAL'",
      "'異⑹쟾???섏??딆쑝硫? 異⑹쟾???곌껐?먮룄 諛섏쓳???놁뒿?덈떎.'",
      "'??'",
      "''",
      "NULL",
      "NULL",
      "NULL",
      "NULL",
      "'2026-01-28 04:34:40.104'",
      "'2026-01-28 04:34:40.110'",
      "NULL",
      "NULL",
      "NULL",
      "'2026-01-28 04:34:40.110'",
      "'2026-01-28 04:34:40.110'",
      "'洹몃줈??",
      "''",
      "'寃쎈궓 吏꾩＜??異⑹쓽濡?146(以묓씎 S?대옒???뷀띁?ㅽ듃) 605??602??",
      "'010-2570-1521'",
      "NULL",
      "NULL",
      "NULL",
      "'2024-06-30 00:00:00.000'",
      "''",
      "NULL",
      "''"
    ],
    "set": [
      "'cmkxj704u00055z7hneamhm2q'",
      "'AS-20260128-002'",
      "'AS-20260128-002'",
      "'cmkxj704q00035z7hg5br0t7h'",
      "NULL",
      "'?뺤???",
      "'REPAIR'",
      "'OTHER'",
      "'AS'",
      "'NORMAL'",
      "'異⑹쟾???섏??딆쑝硫? 異⑹쟾???곌껐?먮룄 諛섏쓳???놁뒿?덈떎.'",
      "'??'",
      "''",
      "NULL",
      "NULL",
      "NULL",
      "NULL",
      "'2026-01-28 04:34:40.104'",
      "'2026-01-28 04:34:40.110'",
      "NULL",
      "NULL",
      "NULL",
      "'2026-01-28 04:34:40.110'",
      "'2026-01-28 04:34:59.450'",
      "'洹몃줈??",
      "''",
      "'寃쎈궓 吏꾩＜??異⑹쓽濡?146(以묓씎 S?대옒???뷀띁?ㅽ듃) 605??602??",
      "'010-2570-1521'",
      "'2026-01-28 00:00:00.000'",
      "NULL",
      "NULL",
      "'2024-06-30 00:00:00.000'",
      "''",
      "NULL",
      "''"
    ],
    "mode": "SET"
  },
  {
    "timestamp": "2026-01-28 16:43:29",
    "operation": "INSERT",
    "table": "crm_ai_web.afterservice",
    "values": [
      "'cmkxpxtye00075z7hmjvdu4gg'",
      "'AS-20260128-003'",
      "'AS-20260128-003'",
      "'cmkuuwdyn0dzno40syrurdl54'",
      "NULL",
      "'?댁쥌誘?",
      "'REPAIR'",
      "'OTHER'",
      "'RECEIVED'",
      "'NORMAL'",
      "'led?????ㅼ뼱?ㅻ굹 ?뚯븘媛???뚮━媛 ?ㅻ━吏 ?딆쓬'",
      "'??'",
      "''",
      "NULL",
      "NULL",
      "NULL",
      "NULL",
      "'2026-01-28 07:43:29.508'",
      "'2026-01-28 07:43:29.510'",
      "NULL",
      "NULL",
      "NULL",
      "'2026-01-28 07:43:29.510'",
      "'2026-01-28 07:43:29.510'",
      "'?댄뵾?ъ쫰'",
      "''",
      "'寃쎄린??源?ъ떆 ?띾Т濡?9踰덇만 51 (?띾Т?? ?밴끝留덉쓣?붾뱶硫붾Ⅴ?붿븰?꾪뙆?? 327-104'",
      "'010-3675-4754'",
      "NULL",
      "NULL",
      "NULL",
      "'2025-12-18 00:00:00.000'",
      "''",
      "NULL",
      "''"
    ],
    "mode": "SET"
  },
  {
    "timestamp": "2026-01-28 16:43:41",
    "operation": "UPDATE",
    "table": "crm_ai_web.afterservice",
    "where": [
      "'cmkxpxtye00075z7hmjvdu4gg'",
      "'AS-20260128-003'",
      "'AS-20260128-003'",
      "'cmkuuwdyn0dzno40syrurdl54'",
      "NULL",
      "'?댁쥌誘?",
      "'REPAIR'",
      "'OTHER'",
      "'RECEIVED'",
      "'NORMAL'",
      "'led?????ㅼ뼱?ㅻ굹 ?뚯븘媛???뚮━媛 ?ㅻ━吏 ?딆쓬'",
      "'??'",
      "''",
      "NULL",
      "NULL",
      "NULL",
      "NULL",
      "'2026-01-28 07:43:29.508'",
      "'2026-01-28 07:43:29.510'",
      "NULL",
      "NULL",
      "NULL",
      "'2026-01-28 07:43:29.510'",
      "'2026-01-28 07:43:29.510'",
      "'?댄뵾?ъ쫰'",
      "''",
      "'寃쎄린??源?ъ떆 ?띾Т濡?9踰덇만 51 (?띾Т?? ?밴끝留덉쓣?붾뱶硫붾Ⅴ?붿븰?꾪뙆?? 327-104'",
      "'010-3675-4754'",
      "NULL",
      "NULL",
      "NULL",
      "'2025-12-18 00:00:00.000'",
      "''",
      "NULL",
      "''"
    ],
    "set": [
      "'cmkxpxtye00075z7hmjvdu4gg'",
      "'AS-20260128-003'",
      "'AS-20260128-003'",
      "'cmkuuwdyn0dzno40syrurdl54'",
      "NULL",
      "'?댁쥌誘?",
      "'REPAIR'",
      "'OTHER'",
      "'AS'",
      "'NORMAL'",
      "'led?????ㅼ뼱?ㅻ굹 ?뚯븘媛???뚮━媛 ?ㅻ━吏 ?딆쓬'",
      "'??'",
      "''",
      "NULL",
      "NULL",
      "NULL",
      "NULL",
      "'2026-01-28 07:43:29.508'",
      "'2026-01-28 07:43:29.510'",
      "NULL",
      "NULL",
      "NULL",
      "'2026-01-28 07:43:29.510'",
      "'2026-01-28 07:43:41.190'",
      "'?댄뵾?ъ쫰'",
      "''",
      "'寃쎄린??源?ъ떆 ?띾Т濡?9踰덇만 51 (?띾Т?? ?밴끝留덉쓣?붾뱶硫붾Ⅴ?붿븰?꾪뙆?? 327-104'",
      "'010-3675-4754'",
      "NULL",
      "'2026-01-28 00:00:00.000'",
      "NULL",
      "'2025-12-18 00:00:00.000'",
      "''",
      "NULL",
      "''"
    ],
    "mode": "SET"
  },
  {
    "timestamp": "2026-01-28 20:17:53",
    "operation": "INSERT",
    "table": "crm_ai_web.order",
    "values": [
      "'cmkxxljwi00095z7hywtqs0i5'",
      "'ORD-2024-001'",
      "'cmkb4qu3x000dpawc76qb55wj'",
      "'2026-01-28 00:00:00.000'",
      "1003000.00",
      "'PENDING'",
      "'?댄뵾?ъ쫰'",
      "'?대뱶4'",
      "NULL",
      "NULL",
      "NULL",
      "NULL",
      "NULL",
      "NULL",
      "3000.00",
      "'?띻만??",
      "'02-1234-5679'",
      "NULL",
      "''",
      "NULL",
      "1",
      "1000000.00",
      "NULL",
      "NULL",
      "NULL",
      "NULL",
      "NULL",
      "'2026-01-28 11:17:53.539'",
      "'2026-01-28 11:17:53.539'",
      "NULL",
      "''",
      "'臾몄븵???붿＜?몄슂'",
      "NULL",
      "NULL",
      "'?쒖슱??媛뺣궓援??뚰뿤?濡?123'",
      "'02-1234-5679'",
      "'12345'",
      "0"
    ],
    "mode": "SET"
  },
  {
    "timestamp": "2026-01-28 20:19:06",
    "operation": "UPDATE",
    "table": "crm_ai_web.order",
    "where": [
      "'cmkxxljwi00095z7hywtqs0i5'",
      "'ORD-2024-001'",
      "'cmkb4qu3x000dpawc76qb55wj'",
      "'2026-01-28 00:00:00.000'",
      "1003000.00",
      "'PENDING'",
      "'?댄뵾?ъ쫰'",
      "'?대뱶4'",
      "NULL",
      "NULL",
      "NULL",
      "NULL",
      "NULL",
      "NULL",
      "3000.00",
      "'?띻만??",
      "'02-1234-5679'",
      "NULL",
      "''",
      "NULL",
      "1",
      "1000000.00",
      "NULL",
      "NULL",
      "NULL",
      "NULL",
      "NULL",
      "'2026-01-28 11:17:53.539'",
      "'2026-01-28 11:17:53.539'",
      "NULL",
      "''",
      "'臾몄븵???붿＜?몄슂'",
      "NULL",
      "NULL",
      "'?쒖슱??媛뺣궓援??뚰뿤?濡?123'",
      "'02-1234-5679'",
      "'12345'",
      "0"
    ],
    "set": [
      "'cmkxxljwi00095z7hywtqs0i5'",
      "'ORD-2024-001'",
      "'cmkb4qu3x000dpawc76qb55wj'",
      "'2026-01-28 00:00:00.000'",
      "1003000.00",
      "'PENDING'",
      "'?댄뵾?ъ쫰'",
      "'?대뱶4'",
      "NULL",
      "NULL",
      "NULL",
      "NULL",
      "NULL",
      "NULL",
      "3000.00",
      "'?띻만??",
      "'02-1234-5679'",
      "NULL",
      "''",
      "NULL",
      "1",
      "1000000.00",
      "NULL",
      "NULL",
      "NULL",
      "NULL",
      "NULL",
      "'2026-01-28 11:17:53.539'",
      "'2026-01-28 11:19:06.514'",
      "NULL",
      "''",
      "'臾몄븵???붿＜?몄슂'",
      "NULL",
      "NULL",
      "'?쒖슱??媛뺣궓援??뚰뿤?濡?123'",
      "'02-1234-5679'",
      "'12345'",
      "1"
    ],
    "mode": "SET"
  },
  {
    "timestamp": "2026-01-28 20:58:14",
    "operation": "UPDATE",
    "table": "crm_ai_web.order",
    "where": [
      "'cmkxxljwi00095z7hywtqs0i5'",
      "'ORD-2024-001'",
      "'cmkb4qu3x000dpawc76qb55wj'",
      "'2026-01-28 00:00:00.000'",
      "1003000.00",
      "'PENDING'",
      "'?댄뵾?ъ쫰'",
      "'?대뱶4'",
      "NULL",
      "NULL",
      "NULL",
      "NULL",
      "NULL",
      "NULL",
      "3000.00",
      "'?띻만??",
      "'02-1234-5679'",
      "NULL",
      "''",
      "NULL",
      "1",
      "1000000.00",
      "NULL",
      "NULL",
      "NULL",
      "NULL",
      "NULL",
      "'2026-01-28 11:17:53.539'",
      "'2026-01-28 11:19:06.514'",
      "NULL",
      "''",
      "'臾몄븵???붿＜?몄슂'",
      "NULL",
      "NULL",
      "'?쒖슱??媛뺣궓援??뚰뿤?濡?123'",
      "'02-1234-5679'",
      "'12345'",
      "1"
    ],
    "set": [
      "'cmkxxljwi00095z7hywtqs0i5'",
      "'ORD-2024-001'",
      "'cmkb4qu3x000dpawc76qb55wj'",
      "'2026-01-28 00:00:00.000'",
      "1003000.00",
      "'SHIPPED'",
      "'?댄뵾?ъ쫰'",
      "'?대뱶4'",
      "NULL",
      "NULL",
      "NULL",
      "NULL",
      "NULL",
      "NULL",
      "3000.00",
      "'?띻만??",
      "'02-1234-5679'",
      "NULL",
      "'123'",
      "NULL",
      "1",
      "1000000.00",
      "NULL",
      "NULL",
      "NULL",
      "NULL",
      "NULL",
      "'2026-01-28 11:17:53.539'",
      "'2026-01-28 11:58:14.796'",
      "NULL",
      "'CJ'",
      "'臾몄븵???붿＜?몄슂'",
      "NULL",
      "NULL",
      "'?쒖슱??媛뺣궓援??뚰뿤?濡?123'",
      "'02-1234-5679'",
      "'12345'",
      "1"
    ],
    "mode": "SET"
  },
  {
    "timestamp": "2026-01-28 20:58:19",
    "operation": "UPDATE",
    "table": "crm_ai_web.order",
    "where": [
      "'cmkxxljwi00095z7hywtqs0i5'",
      "'ORD-2024-001'",
      "'cmkb4qu3x000dpawc76qb55wj'",
      "'2026-01-28 00:00:00.000'",
      "1003000.00",
      "'SHIPPED'",
      "'?댄뵾?ъ쫰'",
      "'?대뱶4'",
      "NULL",
      "NULL",
      "NULL",
      "NULL",
      "NULL",
      "NULL",
      "3000.00",
      "'?띻만??",
      "'02-1234-5679'",
      "NULL",
      "'123'",
      "NULL",
      "1",
      "1000000.00",
      "NULL",
      "NULL",
      "NULL",
      "NULL",
      "NULL",
      "'2026-01-28 11:17:53.539'",
      "'2026-01-28 11:58:14.796'",
      "NULL",
      "'CJ'",
      "'臾몄븵???붿＜?몄슂'",
      "NULL",
      "NULL",
      "'?쒖슱??媛뺣궓援??뚰뿤?濡?123'",
      "'02-1234-5679'",
      "'12345'",
      "1"
    ],
    "set": [
      "'cmkxxljwi00095z7hywtqs0i5'",
      "'ORD-2024-001'",
      "'cmkb4qu3x000dpawc76qb55wj'",
      "'2026-01-28 00:00:00.000'",
      "1003000.00",
      "'SHIPPED'",
      "'?댄뵾?ъ쫰'",
      "'?대뱶4'",
      "NULL",
      "NULL",
      "NULL",
      "NULL",
      "NULL",
      "NULL",
      "3000.00",
      "'?띻만??",
      "'02-1234-5679'",
      "NULL",
      "'123'",
      "NULL",
      "1",
      "1000000.00",
      "NULL",
      "NULL",
      "NULL",
      "NULL",
      "NULL",
      "'2026-01-28 11:17:53.539'",
      "'2026-01-28 11:58:19.636'",
      "NULL",
      "'CJ'",
      "'臾몄븵???붿＜?몄슂'",
      "NULL",
      "NULL",
      "'?쒖슱??媛뺣궓援??뚰뿤?濡?123'",
      "'02-1234-5679'",
      "'12345'",
      "1"
    ],
    "mode": "SET"
  },
  {
    "timestamp": "2026-01-28 20:58:30",
    "operation": "UPDATE",
    "table": "crm_ai_web.order",
    "where": [
      "'cmkxxljwi00095z7hywtqs0i5'",
      "'ORD-2024-001'",
      "'cmkb4qu3x000dpawc76qb55wj'",
      "'2026-01-28 00:00:00.000'",
      "1003000.00",
      "'SHIPPED'",
      "'?댄뵾?ъ쫰'",
      "'?대뱶4'",
      "NULL",
      "NULL",
      "NULL",
      "NULL",
      "NULL",
      "NULL",
      "3000.00",
      "'?띻만??",
      "'02-1234-5679'",
      "NULL",
      "'123'",
      "NULL",
      "1",
      "1000000.00",
      "NULL",
      "NULL",
      "NULL",
      "NULL",
      "NULL",
      "'2026-01-28 11:17:53.539'",
      "'2026-01-28 11:58:19.636'",
      "NULL",
      "'CJ'",
      "'臾몄븵???붿＜?몄슂'",
      "NULL",
      "NULL",
      "'?쒖슱??媛뺣궓援??뚰뿤?濡?123'",
      "'02-1234-5679'",
      "'12345'",
      "1"
    ],
    "set": [
      "'cmkxxljwi00095z7hywtqs0i5'",
      "'ORD-2024-001'",
      "'cmkb4qu3x000dpawc76qb55wj'",
      "'2026-01-28 00:00:00.000'",
      "1003000.00",
      "'SHIPPED'",
      "'?댄뵾?ъ쫰'",
      "'?대뱶4'",
      "NULL",
      "NULL",
      "NULL",
      "NULL",
      "NULL",
      "NULL",
      "3000.00",
      "'?띻만??",
      "'02-1234-5679'",
      "NULL",
      "'123'",
      "NULL",
      "1",
      "1000000.00",
      "NULL",
      "NULL",
      "NULL",
      "NULL",
      "NULL",
      "'2026-01-28 11:17:53.539'",
      "'2026-01-28 11:58:30.172'",
      "NULL",
      "'CJ'",
      "'臾몄븵???붿＜?몄슂'",
      "NULL",
      "NULL",
      "'?쒖슱??媛뺣궓援??뚰뿤?濡?123'",
      "'02-1234-5679'",
      "'12345'",
      "0"
    ],
    "mode": "SET"
  },
  {
    "timestamp": "2026-01-28 20:58:30",
    "operation": "UPDATE",
    "table": "crm_ai_web.order",
    "where": [
      "'cmkxxljwi00095z7hywtqs0i5'",
      "'ORD-2024-001'",
      "'cmkb4qu3x000dpawc76qb55wj'",
      "'2026-01-28 00:00:00.000'",
      "1003000.00",
      "'SHIPPED'",
      "'?댄뵾?ъ쫰'",
      "'?대뱶4'",
      "NULL",
      "NULL",
      "NULL",
      "NULL",
      "NULL",
      "NULL",
      "3000.00",
      "'?띻만??",
      "'02-1234-5679'",
      "NULL",
      "'123'",
      "NULL",
      "1",
      "1000000.00",
      "NULL",
      "NULL",
      "NULL",
      "NULL",
      "NULL",
      "'2026-01-28 11:17:53.539'",
      "'2026-01-28 11:58:30.172'",
      "NULL",
      "'CJ'",
      "'臾몄븵???붿＜?몄슂'",
      "NULL",
      "NULL",
      "'?쒖슱??媛뺣궓援??뚰뿤?濡?123'",
      "'02-1234-5679'",
      "'12345'",
      "0"
    ],
    "set": [
      "'cmkxxljwi00095z7hywtqs0i5'",
      "'ORD-2024-001'",
      "'cmkb4qu3x000dpawc76qb55wj'",
      "'2026-01-28 00:00:00.000'",
      "1003000.00",
      "'SHIPPED'",
      "'?댄뵾?ъ쫰'",
      "'?대뱶4'",
      "NULL",
      "NULL",
      "NULL",
      "NULL",
      "NULL",
      "NULL",
      "3000.00",
      "'?띻만??",
      "'02-1234-5679'",
      "NULL",
      "'123'",
      "NULL",
      "1",
      "1000000.00",
      "NULL",
      "NULL",
      "NULL",
      "NULL",
      "NULL",
      "'2026-01-28 11:17:53.539'",
      "'2026-01-28 11:58:30.814'",
      "NULL",
      "'CJ'",
      "'臾몄븵???붿＜?몄슂'",
      "NULL",
      "NULL",
      "'?쒖슱??媛뺣궓援??뚰뿤?濡?123'",
      "'02-1234-5679'",
      "'12345'",
      "1"
    ],
    "mode": "SET"
  },
  {
    "timestamp": "2026-01-28 20:58:33",
    "operation": "UPDATE",
    "table": "crm_ai_web.order",
    "where": [
      "'cmkxxljwi00095z7hywtqs0i5'",
      "'ORD-2024-001'",
      "'cmkb4qu3x000dpawc76qb55wj'",
      "'2026-01-28 00:00:00.000'",
      "1003000.00",
      "'SHIPPED'",
      "'?댄뵾?ъ쫰'",
      "'?대뱶4'",
      "NULL",
      "NULL",
      "NULL",
      "NULL",
      "NULL",
      "NULL",
      "3000.00",
      "'?띻만??",
      "'02-1234-5679'",
      "NULL",
      "'123'",
      "NULL",
      "1",
      "1000000.00",
      "NULL",
      "NULL",
      "NULL",
      "NULL",
      "NULL",
      "'2026-01-28 11:17:53.539'",
      "'2026-01-28 11:58:30.814'",
      "NULL",
      "'CJ'",
      "'臾몄븵???붿＜?몄슂'",
      "NULL",
      "NULL",
      "'?쒖슱??媛뺣궓援??뚰뿤?濡?123'",
      "'02-1234-5679'",
      "'12345'",
      "1"
    ],
    "set": [
      "'cmkxxljwi00095z7hywtqs0i5'",
      "'ORD-2024-001'",
      "'cmkb4qu3x000dpawc76qb55wj'",
      "'2026-01-28 00:00:00.000'",
      "1003000.00",
      "'SHIPPED'",
      "'?댄뵾?ъ쫰'",
      "'?대뱶4'",
      "NULL",
      "NULL",
      "NULL",
      "NULL",
      "NULL",
      "NULL",
      "3000.00",
      "'?띻만??",
      "'02-1234-5679'",
      "NULL",
      "'123'",
      "NULL",
      "1",
      "1000000.00",
      "NULL",
      "NULL",
      "NULL",
      "NULL",
      "NULL",
      "'2026-01-28 11:17:53.539'",
      "'2026-01-28 11:58:33.533'",
      "NULL",
      "'CJ'",
      "'臾몄븵???붿＜?몄슂'",
      "NULL",
      "NULL",
      "'?쒖슱??媛뺣궓援??뚰뿤?濡?123'",
      "'02-1234-5679'",
      "'12345'",
      "0"
    ],
    "mode": "SET"
  },
  {
    "timestamp": "2026-01-28 20:58:36",
    "operation": "UPDATE",
    "table": "crm_ai_web.order",
    "where": [
      "'cmkxxljwi00095z7hywtqs0i5'",
      "'ORD-2024-001'",
      "'cmkb4qu3x000dpawc76qb55wj'",
      "'2026-01-28 00:00:00.000'",
      "1003000.00",
      "'SHIPPED'",
      "'?댄뵾?ъ쫰'",
      "'?대뱶4'",
      "NULL",
      "NULL",
      "NULL",
      "NULL",
      "NULL",
      "NULL",
      "3000.00",
      "'?띻만??",
      "'02-1234-5679'",
      "NULL",
      "'123'",
      "NULL",
      "1",
      "1000000.00",
      "NULL",
      "NULL",
      "NULL",
      "NULL",
      "NULL",
      "'2026-01-28 11:17:53.539'",
      "'2026-01-28 11:58:33.533'",
      "NULL",
      "'CJ'",
      "'臾몄븵???붿＜?몄슂'",
      "NULL",
      "NULL",
      "'?쒖슱??媛뺣궓援??뚰뿤?濡?123'",
      "'02-1234-5679'",
      "'12345'",
      "0"
    ],
    "set": [
      "'cmkxxljwi00095z7hywtqs0i5'",
      "'ORD-2024-001'",
      "'cmkb4qu3x000dpawc76qb55wj'",
      "'2026-01-28 00:00:00.000'",
      "1003000.00",
      "'SHIPPED'",
      "'?댄뵾?ъ쫰'",
      "'?대뱶4'",
      "NULL",
      "NULL",
      "NULL",
      "NULL",
      "NULL",
      "NULL",
      "3000.00",
      "'?띻만??",
      "'02-1234-5679'",
      "NULL",
      "'123'",
      "NULL",
      "1",
      "1000000.00",
      "NULL",
      "NULL",
      "NULL",
      "NULL",
      "NULL",
      "'2026-01-28 11:17:53.539'",
      "'2026-01-28 11:58:36.266'",
      "NULL",
      "'CJ'",
      "'臾몄븵???붿＜?몄슂'",
      "NULL",
      "NULL",
      "'?쒖슱??媛뺣궓援??뚰뿤?濡?123'",
      "'02-1234-5679'",
      "'12345'",
      "1"
    ],
    "mode": "SET"
  },
  {
    "timestamp": "2026-01-28 20:58:38",
    "operation": "UPDATE",
    "table": "crm_ai_web.order",
    "where": [
      "'cmkxxljwi00095z7hywtqs0i5'",
      "'ORD-2024-001'",
      "'cmkb4qu3x000dpawc76qb55wj'",
      "'2026-01-28 00:00:00.000'",
      "1003000.00",
      "'SHIPPED'",
      "'?댄뵾?ъ쫰'",
      "'?대뱶4'",
      "NULL",
      "NULL",
      "NULL",
      "NULL",
      "NULL",
      "NULL",
      "3000.00",
      "'?띻만??",
      "'02-1234-5679'",
      "NULL",
      "'123'",
      "NULL",
      "1",
      "1000000.00",
      "NULL",
      "NULL",
      "NULL",
      "NULL",
      "NULL",
      "'2026-01-28 11:17:53.539'",
      "'2026-01-28 11:58:36.266'",
      "NULL",
      "'CJ'",
      "'臾몄븵???붿＜?몄슂'",
      "NULL",
      "NULL",
      "'?쒖슱??媛뺣궓援??뚰뿤?濡?123'",
      "'02-1234-5679'",
      "'12345'",
      "1"
    ],
    "set": [
      "'cmkxxljwi00095z7hywtqs0i5'",
      "'ORD-2024-001'",
      "'cmkb4qu3x000dpawc76qb55wj'",
      "'2026-01-28 00:00:00.000'",
      "1003000.00",
      "'SHIPPED'",
      "'?댄뵾?ъ쫰'",
      "'?대뱶4'",
      "NULL",
      "NULL",
      "NULL",
      "NULL",
      "NULL",
      "NULL",
      "3000.00",
      "'?띻만??",
      "'02-1234-5679'",
      "NULL",
      "'123'",
      "NULL",
      "1",
      "1000000.00",
      "NULL",
      "NULL",
      "NULL",
      "NULL",
      "NULL",
      "'2026-01-28 11:17:53.539'",
      "'2026-01-28 11:58:38.041'",
      "NULL",
      "'CJ'",
      "'臾몄븵???붿＜?몄슂'",
      "NULL",
      "NULL",
      "'?쒖슱??媛뺣궓援??뚰뿤?濡?123'",
      "'02-1234-5679'",
      "'12345'",
      "0"
    ],
    "mode": "SET"
  },
  {
    "timestamp": "2026-01-28 20:58:44",
    "operation": "INSERT",
    "table": "crm_ai_web.trashbin",
    "values": [
      "'cmkxz22ra000a5z7hb18mx7uh'",
      "'cmkxxljwi00095z7hywtqs0i5'",
      "'Order'",
      "'{\"id\": \"cmkxxljwi00095z7hywtqs0i5\", \"memo\": null, \"items\": [], \"notes\": null, \"status\": \"SHIPPED\", \"courier\": \"CJ\", \"partner\": null, \"giftSent\": false, \"quantity\": 1, \"basePrice\": \"1000000\", \"createdAt\": \"2026-01-28T11:17:53.539Z\", \"orderDate\": \"2026-01-28T00:00:00.000Z\", \"staffName\": null, \"updatedAt\": \"2026-01-28T11:58:38.041Z\", \"customerId\": \"cmkb4qu3x000dpawc76qb55wj\", \"giftOption\": null, \"deliveryMsg\": \"臾몄븵???붿＜?몄슂\", \"orderNumber\": \"ORD-2024-001\", \"orderSource\": \"?댄뵾?ъ쫰\", \"ordererName\": null, \"productInfo\": \"?대뱶4\", \"productName\": null, \"shippingFee\": \"3000\", \"totalAmount\": \"1003000\", \"contactPhone\": null, \"customerName\": null, \"shippingAddr\": null, \"additionalFee\": null, \"customerEmail\": null, \"customerPhone\": null, \"recipientAddr\": \"?쒖슱??媛뺣궓援??뚰뿤?濡?123\", \"recipientName\": \"?띻만??, \"customerMobile\": null, \"recipientPhone\": \"02-1234-5679\", \"shippingMethod\": null, \"shippingStatus\": null, \"trackingNumber\": \"123\", \"recipientMobile\": \"02-1234-5679\", \"recipientZipCode\": \"12345\"}'",
      "NULL",
      "NULL",
      "NULL",
      "'ORD-2024-001'",
      "'?띻만??| ?대뱶4 | ??,003,000'",
      "'2026-02-27 11:58:44.084'",
      "'2026-01-28 11:58:44.086'"
    ],
    "mode": "SET"
  },
  {
    "timestamp": "2026-01-28 20:58:44",
    "operation": "DELETE",
    "table": "crm_ai_web.order",
    "where": [
      "'cmkxxljwi00095z7hywtqs0i5'",
      "'ORD-2024-001'",
      "'cmkb4qu3x000dpawc76qb55wj'",
      "'2026-01-28 00:00:00.000'",
      "1003000.00",
      "'SHIPPED'",
      "'?댄뵾?ъ쫰'",
      "'?대뱶4'",
      "NULL",
      "NULL",
      "NULL",
      "NULL",
      "NULL",
      "NULL",
      "3000.00",
      "'?띻만??",
      "'02-1234-5679'",
      "NULL",
      "'123'",
      "NULL",
      "1",
      "1000000.00",
      "NULL",
      "NULL",
      "NULL",
      "NULL",
      "NULL",
      "'2026-01-28 11:17:53.539'",
      "'2026-01-28 11:58:38.041'",
      "NULL",
      "'CJ'",
      "'臾몄븵???붿＜?몄슂'",
      "NULL",
      "NULL",
      "'?쒖슱??媛뺣궓援??뚰뿤?濡?123'",
      "'02-1234-5679'",
      "'12345'",
      "0"
    ],
    "mode": "WHERE"
  },
  {
    "timestamp": "2026-01-28 20:59:53",
    "operation": "INSERT",
    "table": "crm_ai_web.order",
    "values": [
      "'cmkxz3kcu000c5z7h0odo4wrb'",
      "'ORD-2024-001'",
      "'cmkb4qu3x000dpawc76qb55wj'",
      "'2026-01-28 00:00:00.000'",
      "1003000.00",
      "'PENDING'",
      "'?댄뵾?ъ쫰'",
      "'?대뱶4'",
      "NULL",
      "NULL",
      "NULL",
      "NULL",
      "NULL",
      "NULL",
      "3000.00",
      "'?띻만??",
      "'02-1234-5679'",
      "NULL",
      "''",
      "NULL",
      "1",
      "1000000.00",
      "NULL",
      "NULL",
      "NULL",
      "NULL",
      "NULL",
      "'2026-01-28 11:59:53.550'",
      "'2026-01-28 11:59:53.550'",
      "NULL",
      "''",
      "'臾몄븵???붿＜?몄슂'",
      "NULL",
      "NULL",
      "'?쒖슱??媛뺣궓援??뚰뿤?濡?123'",
      "'02-1234-5679'",
      "'12345'",
      "0"
    ],
    "mode": "SET"
  },
  {
    "timestamp": "2026-01-28 21:01:35",
    "operation": "UPDATE",
    "table": "crm_ai_web.order",
    "where": [
      "'cmkxz3kcu000c5z7h0odo4wrb'",
      "'ORD-2024-001'",
      "'cmkb4qu3x000dpawc76qb55wj'",
      "'2026-01-28 00:00:00.000'",
      "1003000.00",
      "'PENDING'",
      "'?댄뵾?ъ쫰'",
      "'?대뱶4'",
      "NULL",
      "NULL",
      "NULL",
      "NULL",
      "NULL",
      "NULL",
      "3000.00",
      "'?띻만??",
      "'02-1234-5679'",
      "NULL",
      "''",
      "NULL",
      "1",
      "1000000.00",
      "NULL",
      "NULL",
      "NULL",
      "NULL",
      "NULL",
      "'2026-01-28 11:59:53.550'",
      "'2026-01-28 11:59:53.550'",
      "NULL",
      "''",
      "'臾몄븵???붿＜?몄슂'",
      "NULL",
      "NULL",
      "'?쒖슱??媛뺣궓援??뚰뿤?濡?123'",
      "'02-1234-5679'",
      "'12345'",
      "0"
    ],
    "set": [
      "'cmkxz3kcu000c5z7h0odo4wrb'",
      "'ORD-2024-001'",
      "'cmkb4qu3x000dpawc76qb55wj'",
      "'2026-01-28 00:00:00.000'",
      "1003000.00",
      "'SHIPPED'",
      "'?댄뵾?ъ쫰'",
      "'?대뱶4'",
      "NULL",
      "NULL",
      "NULL",
      "NULL",
      "NULL",
      "NULL",
      "3000.00",
      "'?띻만??",
      "'02-1234-5679'",
      "NULL",
      "'1234'",
      "NULL",
      "1",
      "1000000.00",
      "NULL",
      "NULL",
      "NULL",
      "NULL",
      "NULL",
      "'2026-01-28 11:59:53.550'",
      "'2026-01-28 12:01:35.152'",
      "NULL",
      "'CJ'",
      "'臾몄븵???붿＜?몄슂'",
      "NULL",
      "NULL",
      "'?쒖슱??媛뺣궓援??뚰뿤?濡?123'",
      "'02-1234-5679'",
      "'12345'",
      "0"
    ],
    "mode": "SET"
  },
  {
    "timestamp": "2026-01-28 21:01:43",
    "operation": "UPDATE",
    "table": "crm_ai_web.order",
    "where": [
      "'cmkxz3kcu000c5z7h0odo4wrb'",
      "'ORD-2024-001'",
      "'cmkb4qu3x000dpawc76qb55wj'",
      "'2026-01-28 00:00:00.000'",
      "1003000.00",
      "'SHIPPED'",
      "'?댄뵾?ъ쫰'",
      "'?대뱶4'",
      "NULL",
      "NULL",
      "NULL",
      "NULL",
      "NULL",
      "NULL",
      "3000.00",
      "'?띻만??",
      "'02-1234-5679'",
      "NULL",
      "'1234'",
      "NULL",
      "1",
      "1000000.00",
      "NULL",
      "NULL",
      "NULL",
      "NULL",
      "NULL",
      "'2026-01-28 11:59:53.550'",
      "'2026-01-28 12:01:35.152'",
      "NULL",
      "'CJ'",
      "'臾몄븵???붿＜?몄슂'",
      "NULL",
      "NULL",
      "'?쒖슱??媛뺣궓援??뚰뿤?濡?123'",
      "'02-1234-5679'",
      "'12345'",
      "0"
    ],
    "set": [
      "'cmkxz3kcu000c5z7h0odo4wrb'",
      "'ORD-2024-001'",
      "'cmkb4qu3x000dpawc76qb55wj'",
      "'2026-01-28 00:00:00.000'",
      "1003000.00",
      "'SHIPPED'",
      "'?댄뵾?ъ쫰'",
      "'?대뱶4'",
      "NULL",
      "NULL",
      "NULL",
      "NULL",
      "NULL",
      "NULL",
      "3000.00",
      "'?띻만??",
      "'02-1234-5679'",
      "NULL",
      "'1234'",
      "NULL",
      "1",
      "1000000.00",
      "NULL",
      "NULL",
      "NULL",
      "NULL",
      "NULL",
      "'2026-01-28 11:59:53.550'",
      "'2026-01-28 12:01:43.407'",
      "NULL",
      "'CJ'",
      "'臾몄븵???붿＜?몄슂'",
      "NULL",
      "NULL",
      "'?쒖슱??媛뺣궓援??뚰뿤?濡?123'",
      "'02-1234-5679'",
      "'12345'",
      "0"
    ],
    "mode": "SET"
  },
  {
    "timestamp": "2026-01-28 21:01:56",
    "operation": "INSERT",
    "table": "crm_ai_web.trashbin",
    "values": [
      "'cmkxz67a3000d5z7hpyj4xajp'",
      "'cmkxz3kcu000c5z7h0odo4wrb'",
      "'Order'",
      "'{\"id\": \"cmkxz3kcu000c5z7h0odo4wrb\", \"memo\": null, \"items\": [], \"notes\": null, \"status\": \"SHIPPED\", \"courier\": \"CJ\", \"partner\": null, \"giftSent\": false, \"quantity\": 1, \"basePrice\": \"1000000\", \"createdAt\": \"2026-01-28T11:59:53.550Z\", \"orderDate\": \"2026-01-28T00:00:00.000Z\", \"staffName\": null, \"updatedAt\": \"2026-01-28T12:01:43.407Z\", \"customerId\": \"cmkb4qu3x000dpawc76qb55wj\", \"giftOption\": null, \"deliveryMsg\": \"臾몄븵???붿＜?몄슂\", \"orderNumber\": \"ORD-2024-001\", \"orderSource\": \"?댄뵾?ъ쫰\", \"ordererName\": null, \"productInfo\": \"?대뱶4\", \"productName\": null, \"shippingFee\": \"3000\", \"totalAmount\": \"1003000\", \"contactPhone\": null, \"customerName\": null, \"shippingAddr\": null, \"additionalFee\": null, \"customerEmail\": null, \"customerPhone\": null, \"recipientAddr\": \"?쒖슱??媛뺣궓援??뚰뿤?濡?123\", \"recipientName\": \"?띻만??, \"customerMobile\": null, \"recipientPhone\": \"02-1234-5679\", \"shippingMethod\": null, \"shippingStatus\": null, \"trackingNumber\": \"1234\", \"recipientMobile\": \"02-1234-5679\", \"recipientZipCode\": \"12345\"}'",
      "NULL",
      "NULL",
      "NULL",
      "'ORD-2024-001'",
      "'?띻만??| ?대뱶4 | ??,003,000'",
      "'2026-02-27 12:01:56.570'",
      "'2026-01-28 12:01:56.572'"
    ],
    "mode": "SET"
  },
  {
    "timestamp": "2026-01-28 21:01:56",
    "operation": "DELETE",
    "table": "crm_ai_web.order",
    "where": [
      "'cmkxz3kcu000c5z7h0odo4wrb'",
      "'ORD-2024-001'",
      "'cmkb4qu3x000dpawc76qb55wj'",
      "'2026-01-28 00:00:00.000'",
      "1003000.00",
      "'SHIPPED'",
      "'?댄뵾?ъ쫰'",
      "'?대뱶4'",
      "NULL",
      "NULL",
      "NULL",
      "NULL",
      "NULL",
      "NULL",
      "3000.00",
      "'?띻만??",
      "'02-1234-5679'",
      "NULL",
      "'1234'",
      "NULL",
      "1",
      "1000000.00",
      "NULL",
      "NULL",
      "NULL",
      "NULL",
      "NULL",
      "'2026-01-28 11:59:53.550'",
      "'2026-01-28 12:01:43.407'",
      "NULL",
      "'CJ'",
      "'臾몄븵???붿＜?몄슂'",
      "NULL",
      "NULL",
      "'?쒖슱??媛뺣궓援??뚰뿤?濡?123'",
      "'02-1234-5679'",
      "'12345'",
      "0"
    ],
    "mode": "WHERE"
  },
  {
    "timestamp": "2026-01-28 21:02:35",
    "operation": "INSERT",
    "table": "crm_ai_web.order",
    "values": [
      "'cmkxz71em0001sn9ljv3s82jw'",
      "'ORD-2024-001'",
      "'cmkb4qu3x000dpawc76qb55wj'",
      "'2026-01-28 00:00:00.000'",
      "1003000.00",
      "'PENDING'",
      "'?댄뵾?ъ쫰'",
      "'?대뱶4'",
      "NULL",
      "NULL",
      "NULL",
      "NULL",
      "NULL",
      "NULL",
      "3000.00",
      "'?띻만??",
      "'02-1234-5679'",
      "NULL",
      "''",
      "NULL",
      "1",
      "1000000.00",
      "NULL",
      "NULL",
      "NULL",
      "NULL",
      "NULL",
      "'2026-01-28 12:02:35.614'",
      "'2026-01-28 12:02:35.614'",
      "NULL",
      "''",
      "'臾몄븵???붿＜?몄슂'",
      "NULL",
      "NULL",
      "'?쒖슱??媛뺣궓援??뚰뿤?濡?123'",
      "'02-1234-5679'",
      "'12345'",
      "0"
    ],
    "mode": "SET"
  }
]